lightpdf_aipdf_backend/__init__.py
lightpdf_aipdf_backend/__main__.py
lightpdf_aipdf_backend/app.py
lightpdf_aipdf_backend/chat_handler.py
lightpdf_aipdf_backend/cli.py
lightpdf_aipdf_backend/config.py
lightpdf_aipdf_backend/file_handler.py
lightpdf_aipdf_backend/main.py
lightpdf_aipdf_backend/models.py
lightpdf_aipdf_backend/oss_config.py
lightpdf_aipdf_backend/state.py
lightpdf_aipdf_backend/tasks.py
lightpdf_aipdf_backend/tools.py
lightpdf_aipdf_backend/utils.py
lightpdf_aipdf_backend-0.1.82.dist-info/METADATA
lightpdf_aipdf_backend-0.1.82.dist-info/WHEEL
lightpdf_aipdf_backend-0.1.82.dist-info/entry_points.txt
lightpdf_aipdf_backend-0.1.82.dist-info/RECORD
