Metadata-Version: 2.4
Name: lightpdf-aipdf-backend
Version: 0.1.82
Summary: Backend API for LightPDF AI-PDF
Author: LightPDF Team
License: Proprietary
Requires-Python: >=3.10
Requires-Dist: fastapi
Requires-Dist: mcp
Requires-Dist: mcp[cli]
Requires-Dist: openai
Requires-Dist: oss2
Requires-Dist: pydantic
Requires-Dist: python-dotenv
Requires-Dist: python-multipart
Requires-Dist: redis
Requires-Dist: uv
Requires-Dist: uvicorn
Provides-Extra: dev
Requires-Dist: black; extra == 'dev'
Requires-Dist: isort; extra == 'dev'
Requires-Dist: pytest; extra == 'dev'
